mokebetoolzxp/__init__.py
mokebetoolzxp/a.py
mokebetoolzxp-2.0.0.dist-info/METADATA
mokebetoolzxp-2.0.0.dist-info/WHEEL
mokebetoolzxp-2.0.0.dist-info/RECORD
