Metadata-Version: 2.1
Name: mokebetoolzxp
Version: 2.0.0
Summary: 
Author: mg25683
Author-email: maciek.gluszak6@gmail.com
Requires-Python: >=3.10,<4.0
Classifier: Programming Language :: Python :: 3
Classifier: Programming Language :: Python :: 3.10
Classifier: Programming Language :: Python :: 3.11
Requires-Dist: pandas (>=1.5.3,<2.0.0)
